dinterpol/__init__.py
dinterpol/about.py
dinterpol/attr2key.py
dinterpol/template.py
dinterpol/test_attr2key.py
dinterpol/test_attribute_convert.py
dinterpol/test_template.py
dinterpol-0.3.5.dist-info/LICENSE
dinterpol-0.3.5.dist-info/METADATA
dinterpol-0.3.5.dist-info/WHEEL
dinterpol-0.3.5.dist-info/top_level.txt
dinterpol-0.3.5.dist-info/zip-safe
dinterpol-0.3.5.dist-info/RECORD
