Metadata-Version: 2.1
Name: dinterpol
Version: 0.3.5
Summary: data interpolation templating engine
Home-page: https://github.com/Openpipe/dinterpol
Author: João Pinto
Author-email: lamego.pinto@gmail.com
License: Apache-2
Platform: UNKNOWN
Classifier: Development Status :: 1 - Planning
Classifier: Environment :: Console
Classifier: Intended Audience :: Developers
Classifier: Intended Audience :: Information Technology
Classifier: Intended Audience :: System Administrators
Classifier: License :: Freely Distributable
Classifier: License :: OSI Approved :: Apache Software License
Classifier: Operating System :: OS Independent
Classifier: Programming Language :: Python
Classifier: Programming Language :: Python :: 3.7
Classifier: Topic :: Software Development :: Testing
Classifier: Topic :: Utilities
Requires-Dist: click
Requires-Dist: enclosed
